kshell_utilities/__init__.py
kshell_utilities/collect_logs.py
kshell_utilities/compare.py
kshell_utilities/count_dim.py
kshell_utilities/data_structures.py
kshell_utilities/deprecated.py
kshell_utilities/general_utilities.py
kshell_utilities/kshell_exceptions.py
kshell_utilities/kshell_utilities.py
kshell_utilities/kshell_utilities_tmp.py
kshell_utilities/loaders.py
kshell_utilities/other_tools.py
kshell_utilities/parameters.py
kshell_utilities/partition_compare.py
kshell_utilities/partition_editor.py
kshell_utilities/partition_tools.py
kshell_utilities/script_editing.py
tests/__init__.py
tests/test_all.py
tests/test_partition_editor.py
tests/test_spin_parity_list.py
kshell_utilities-1.5.1.0.dist-info/LICENSE
kshell_utilities-1.5.1.0.dist-info/METADATA
kshell_utilities-1.5.1.0.dist-info/WHEEL
kshell_utilities-1.5.1.0.dist-info/top_level.txt
kshell_utilities-1.5.1.0.dist-info/RECORD
